{
    "category": "custom",
    "description": "ur mum",
    "pattern": [
        [
            false,
            false,
            false,
            false,
            true,
            false,
            false,
            false,
            false,
            false,
            false
        ],
        [
            false,
            false,
            false,
            false,
            false,
            false,
            false,
            false,
            false,
            false,
            true
        ],
        [
            true,
            false,
            false,
            false,
            false,
            false,
            false,
            false,
            false,
            false,
            false
        ],
        [
            false,
            false,
            false,
            false,
            false,
            false,
            false,
            false,
            false,
            false,
            false
        ],
        [
            false,
            false,
            false,
            false,
            false,
            false,
            false,
            false,
            false,
            false,
            false
        ],
        [
            false,
            false,
            false,
            false,
            false,
            false,
            false,
            false,
            false,
            false,
            false
        ],
        [
            false,
            false,
            false,
            false,
            false,
            true,
            false,
            false,
            false,
            true,
            false
        ]
    ],
    "id": "uwu",
    "name": "uwu"
}